src/travibot_Vasily566/__init__.py
src/travibot_Vasily566/main.py
travibot-1.0.0.dist-info/METADATA
travibot-1.0.0.dist-info/WHEEL
travibot-1.0.0.dist-info/licenses/LICENSE
travibot-1.0.0.dist-info/RECORD
