Metadata-Version: 2.1
Name: travibot
Version: 1.0.0
Summary: Simple automatic travian bot that automaticly build ur vilage/villages.
Project-URL: Homepage, https://github.com/Vasiliy566/travian_bot
Project-URL: Bug Tracker, https://github.com/Vasiliy566/travian_bot/issues
Author-email: Isaev Vasily <vasyaisaev31@gmail.com>
License-File: LICENSE
Classifier: License :: OSI Approved :: MIT License
Classifier: Operating System :: OS Independent
Classifier: Programming Language :: Python :: 3
Requires-Python: >=3.7
Requires-Dist: selenium
